<?xml version="1.0" encoding="utf-8"?>
<!DOCTYPE install PUBLIC "-//Joomla! 1.7//DTD template 1.0//EN" "http://www.joomla.org/xml/dtd/1.7/template-install.dtd">
<extension version="2.5" type="template" client="site" method="upgrade">
	<name>LSPB</name>
	<creationDate>2015-11-20</creationDate>
	<author>Ovidijus Baublys</author>
	<authorEmail>ovidijus.baublys@gmail.com</authorEmail>
	<authorUrl>http://www.ovi-web.lt</authorUrl>
	<copyright>Ovidijus Baublys 2015</copyright>
	<license>GNU/GPL</license>
	<version>0.3</version>
	<description>LSPB</description>
	<files>
		<filename>index.php</filename>
		<filename>logic.php</filename>
		<filename>templateDetails.xml</filename>
		<folder>bootstrap-sass</folder>
		<folder>css</folder>
		<folder>js</folder>
		<folder>sass</folder>
		<folder>fonts</folder>
		<folder>images</folder>
	</files>
	<positions>
		<position>menu</position>
		<position>showcase</position>
		<position>homesearch</position>
		<position>content</position>
		<position>content-fluid</position>
		<position>box1</position>
		<position>box2</position>
		<position>box3</position>
		<position>sidebar</position>
		<position>foot-top</position>
		<position>foot-left</position>
		<position>foot-mid</position>
		<position>foot-right</position>
		<position>foot-bottom</position>
	</positions>
</extension>